clud/__init__.py
clud/__main__.py
clud/agent_args.py
clud/agent_cli.py
clud/chat_agent.py
clud/claude_installer.py
clud/cli.py
clud/cli_args.py
clud/emoji_util.py
clud/git_precheck.py
clud/json_formatter.py
clud/kanban_manager.py
clud/output_filter.py
clud/print_filter.py
clud/project_init.py
clud/secrets.py
clud/settings.py
clud/settings_manager.py
clud/shell_config.py
clud/sketch.py
clud/spinner.py
clud/streaming_parser.py
clud/streaming_ui.py
clud/sub_clud_runner.py
clud/task.py
clud/telegram_bot.py
clud/type_defs.py
clud/web_compile.py
clud/agent/__init__.py
clud/agent/claude_finder.py
clud/agent/command_builder.py
clud/agent/completion.py
clud/agent/config.py
clud/agent/exceptions.py
clud/agent/foreground_args.py
clud/agent/github.py
clud/agent/hooks.py
clud/agent/lint_runner.py
clud/agent/loop_executor.py
clud/agent/loop_logger.py
clud/agent/motivation.py
clud/agent/runner.py
clud/agent/subprocess.py
clud/agent/task_info.py
clud/agent/task_manager.py
clud/agent/tracking.py
clud/agent/user_input.py
clud/agent/commands/__init__.py
clud/agent/commands/api_server.py
clud/agent/commands/code.py
clud/agent/commands/codeup.py
clud/agent/commands/fix.py
clud/agent/commands/info.py
clud/agent/commands/init_loop.py
clud/agent/commands/install_claude.py
clud/agent/commands/kanban.py
clud/agent/commands/lint.py
clud/agent/commands/telegram.py
clud/agent/commands/telegram_server.py
clud/agent/commands/test.py
clud/agent/commands/webui.py
clud/api/__init__.py
clud/api/instance_manager.py
clud/api/message_handler.py
clud/api/models.py
clud/api/server.py
clud/assets/example.txt
clud/backlog/__init__.py
clud/backlog/parser.py
clud/cluster/__init__.py
clud/cluster/app.py
clud/cluster/auth.py
clud/cluster/auth_dependencies.py
clud/cluster/cli.py
clud/cluster/config.py
clud/cluster/database.py
clud/cluster/models.py
clud/cluster/telegram_bot.py
clud/cluster/websocket_handlers.py
clud/cluster/assets/example.txt
clud/cluster/routes/__init__.py
clud/cluster/routes/agents.py
clud-1.1.0.dist-info/licenses/LICENSE
clud-1.1.0.dist-info/METADATA
clud-1.1.0.dist-info/WHEEL
clud-1.1.0.dist-info/entry_points.txt
clud-1.1.0.dist-info/top_level.txt
clud-1.1.0.dist-info/RECORD
