Metadata-Version: 2.4
Name: clud
Version: 1.1.0
Summary: Claude Code in YOLO mode
License: BSD 3-Clause License
Keywords: claude,cli,ai
Classifier: Programming Language :: Python :: 3
Requires-Python: >=3.10
License-File: LICENSE
Requires-Dist: keyring>=24.0.0
Requires-Dist: fasteners>=0.17.0
Requires-Dist: appdirs>=1.4.4
Requires-Dist: disklru>=0.1.0
Requires-Dist: httpx>=0.24.0
Requires-Dist: pywinpty>=3.0.0; sys_platform == "win32"
Requires-Dist: running-process>=1.0.7
Requires-Dist: nodeenv>=1.8.0
Requires-Dist: nodejs-wheel>=22.0.0
Requires-Dist: fastapi>=0.115.0
Requires-Dist: uvicorn[standard]>=0.32.0
Requires-Dist: markdown2>=2.4.0
Requires-Dist: websockets>=12.0
Requires-Dist: sqlalchemy>=2.0.0
Requires-Dist: aiosqlite>=0.19.0
Requires-Dist: alembic>=1.12.0
Requires-Dist: pydantic>=2.5.0
Requires-Dist: pydantic-settings>=2.1.0
Requires-Dist: python-jose[cryptography]>=3.3.0
Requires-Dist: passlib[bcrypt]>=1.7.4
Requires-Dist: python-multipart>=0.0.6
Requires-Dist: psutil>=5.9.0
Requires-Dist: python-telegram-bot>=20.0
Requires-Dist: codeup>=1.0.22
Requires-Dist: pyyaml>=6.0.0
Requires-Dist: croniter>=1.4.0
Provides-Extra: dev
Requires-Dist: pytest>=7.0.0; extra == "dev"
Requires-Dist: pytest-xdist>=2.0.0; extra == "dev"
Requires-Dist: ruff>=0.1.0; extra == "dev"
Requires-Dist: pyright>=1.1.0; extra == "dev"
Requires-Dist: playwright>=1.40.0; extra == "dev"
Requires-Dist: pytest-playwright>=0.4.0; extra == "dev"
Provides-Extra: keyring-fallbacks
Requires-Dist: keyrings.cryptfile>=1.3.0; extra == "keyring-fallbacks"
Requires-Dist: cryptography>=3.0.0; extra == "keyring-fallbacks"
Provides-Extra: posix
Requires-Dist: zcmds_win32>=1.2.0; sys_platform == "win32" and extra == "posix"
Provides-Extra: full
Requires-Dist: zcmds_win32>=1.2.0; sys_platform == "win32" and extra == "full"
Dynamic: license-file
